Workbook

Sheet  Issue Tracker
A1: 🏨 Hotel Booking Engine — Issue & Error Tracker
A2: Status: 5 of 34 fixed already (incl. the critical AI-assistant restore) • 29 logged as a proactive hardening roadmap — latent risks that surface under live guest load, not current outages. Backend tests green (253 passed); CI/CD strengthened.
A3: ID | B3: Phase | C3: Category | D3: Error / Issue | E3: Description | F3: Root Cause | G3: Recommended Fix | H3: Priority | I3: Status | J3: Assigned To | K3: Reported Date | L3: Target Date | M3: Resolved Date | N3: Resolution Notes | O3: Time to Fix (days) | P3: Remarks
A4: BE-001 | B4: Pre-Development | C4: AI / Cost Governance | D4: Define a per-hotel AI spend budget & billing model | E4: Token usage is already recorded per hotel/day (ai_usage.py -> Redis ai_tokens:{hotel}:{date}); what's missing is a budget ceiling, alert threshold and a bill pass-through decision. ⏱ When it surfaces: As paid AI usage grows across many live hotels. | F4: Cost governance was not defined as a requirement up front. | G4: Set a monthly AI ceiling per plan tier; alert on the existing counters; decide absorbed vs passed-through cost. | H4: High | I4: Open | J4: Tech Lead / Founder | K4: 10/06/2026 | O4: =IF(AND(K4<>"",M4<>""),M4-K4,"") | P4: Protects margin: prevents a slow, invisible LLM-cost creep from showing up only on the monthly invoice.
A5: BE-002 | B5: Pre-Development | C5: Infrastructure / Trust | D5: Pin the trusted reverse-proxy hop for client IP | E5: Rate limiting reads the first X-Forwarded-For value (limiter.py). Behind most proxies the client can set this header, so IP-based limits can be diluted. ⏱ When it surfaces: When someone deliberately rotates X-Forwarded-For to dodge limits. | F5: Deployment trust boundary (which proxy hop is trusted) is not yet pinned. | G5: Read the client IP from the verified proxy hop / CDN header; document the topology. | H5: High | I5: Open | J5: Tech Lead / Founder | K5: 10/06/2026 | O5: =IF(AND(K5<>"",M5<>""),M5-K5,"") | P5: Hardens every IP-based limit (login, booking, AI chat) against header spoofing.
A6: BE-003 | B6: Pre-Development | C6: Reliability / Design | D6: Decide fail-closed vs fail-open for Redis-backed controls | E6: _enforce_hotel_ai_quota and the limiter intentionally fail OPEN if Redis is unreachable so real guests aren't blocked — a deliberate availability choice that trades away cost protection during an outage. ⏱ When it surfaces: Only during a Redis outage coinciding with a traffic/abuse spike. | F6: Availability prioritised over cost-safety; no conservative fallback budget. | G6: Add a conservative in-process fallback cap for cost-bearing controls; alert on Redis health. | H6: Medium | I6: Open | J6: Tech Lead / Founder | K6: 10/06/2026 | O6: =IF(AND(K6<>"",M6<>""),M6-K6,"") | P6: Keeps a floor of abuse/cost protection even when Redis is briefly unavailable.
A7: BE-004 | B7: Pre-Development | C7: Capacity Planning | D7: Run the peak-load test before go-live | E7: A ready load-test script (scripts/load_test.py) and a sizing guide (SCALE_TUNING.md) exist; the test simply needs to be executed at expected peak and the pool/concurrency tuned to the result. ⏱ When it surfaces: At the first real high-traffic moment (sale, campaign, festival). | F7: Go-live checklist item still open. | G7: Run load_test.py on staging at expected peak; set WEB_CONCURRENCY and pool under the Supabase limit. | H7: High | I7: Open | J7: Tech Lead / Founder | K7: 10/06/2026 | O7: =IF(AND(K7<>"",M7<>""),M7-K7,"") | P7: Turns the scaling ceiling into a known number instead of discovering it during a live spike.
A8: BE-005 | B8: Pre-Development | C8: Capacity Planning | D8: Validate the DB connection budget for AI/streaming workloads | E8: Default pool is ~10 conns/worker. AI chat keeps a DB session open during the LLM call, so effective AI concurrency is lower than the raw pool math suggests. ⏱ When it surfaces: As concurrent AI chats rise across busy hotels. | F8: Connection math assumes short requests; long AI requests were not separately modelled. | G8: Model AI concurrency separately; size pool vs Supabase limit; combine with the streaming/session work below. | H8: Medium | I8: Open | J8: Tech Lead / Founder | K8: 10/06/2026 | O8: =IF(AND(K8<>"",M8<>""),M8-K8,"") | P8: Prevents connection-pool pressure from AI traffic affecting the rest of the API.
A9: BE-006 | B9: Pre-Development | C9: Team / Ownership | D9: Assign dedicated backend & frontend engineering ownership | E9: The platform is large (~70 routers, 250+ endpoints, payments, multi-tenant, AI). Today there is no named owner for backend reliability or frontend UX/performance. ⏱ When it surfaces: Continuously — every unowned issue ages without a clear owner. | F9: Project scope outgrew the team. | G9: Hire 1 backend + 1 frontend engineer (scoped on the 'Team & Hiring' sheet). | H9: High | I9: Open | J9: Tech Lead / Founder | K9: 10/06/2026 | O9: =IF(AND(K9<>"",M9<>""),M9-K9,"") | P9: Faster fixes, lower single-maintainer risk, and the Hypercare SLAs become achievable.
A10: BE-007 | B10: Development | C10: AI Agent / Bug | D10: Hotelier AI Assistant crashed on every message (missing logger) | E10: agent.py referenced a module-level `logger` (smart tool selector + settings fetch) that was never defined, so any non-empty query raised NameError and returned 500. ⏱ When it surfaces: Was firing on 100% of hotelier assistant messages. | F10: Missing logging.getLogger in app/core/agent.py. | G10: Add the module logger; add a regression smoke test on the tool-selector path. | H10: Critical | I10: Resolved | J10: Backend Dev | K10: 10/06/2026 | M10: 10/06/2026 | N10: Added module-level logger in app/core/agent.py; added tests/test_ai_agent_smoke.py asserting the tool-selector path never raises NameError. Full suite green (253 passed). | O10: =IF(AND(K10<>"",M10<>""),M10-K10,"") | P10: FIXED: the paid hotelier AI assistant is restored. This was the single biggest functional bug.
A11: BE-008 | B11: Development | C11: AI / Scaling | D11: AI chat holds a DB connection for the whole LLM round-trip | E11: chat.py/agent.py keep the request DB session open while agent.arun() runs (seconds, 1-2 calls) because the agent's tools query the DB mid-call. ⏱ When it surfaces: When many guests chat at the same time (e.g. a campaign). | F11: Request-scoped session spans the slow LLM I/O instead of using short per-tool sessions. | G11: Refactor tools to short-lived sessions / pre-fetch data and release the session before the model call. | H11: High | I11: Open | J11: Backend Dev | K11: 10/06/2026 | O11: =IF(AND(K11<>"",M11<>""),M11-K11,"") | P11: Once addressed, AI concurrency stops competing with the rest of the API for DB connections.
A12: BE-009 | B12: Development | C12: AI / Cost | D12: Error fallback escalated to the expensive 70B model | E12: On any guest-agent error, chat.py retried (without tools) and defaulted to llama-3.3-70b-versatile — pricier than the normal 8B path — after already paying for the failed call. ⏱ When it surfaces: During any transient provider/tool error, multiplied under load. | F12: Fallback defaulted to a large model. | G12: Keep the fallback on the cheap 8B model; single attempt. | H12: High | I12: Resolved | J12: Backend Dev | K12: 10/06/2026 | M12: 10/06/2026 | N12: chat.py fallback now defaults to llama-3.1-8b-instant (cheap) instead of the 70B model. | O12: =IF(AND(K12<>"",M12<>""),M12-K12,"") | P12: FIXED: error storms no longer cost ~2x and no longer jump to a costlier model.
A13: BE-010 | B13: Development | C13: AI / Reliability | D13: Web-search tool could block the worker (sync call, no timeout) | E13: agent.py search_web called DuckDuckGo synchronously on the event loop with no timeout. ⏱ When it surfaces: Whenever the hotelier asks a 'why' question that triggers web search and DDG is slow. | F13: Blocking external call with no SLA on the async loop. | G13: Run it in a thread with a hard timeout; degrade gracefully. | H13: High | I13: Resolved | J13: Backend Dev | K13: 10/06/2026 | M13: 10/06/2026 | N13: search_web now uses asyncio.to_thread + asyncio.wait_for(8s) and returns a graceful message on timeout/failure. | O13: =IF(AND(K13<>"",M13<>""),M13-K13,"") | P13: FIXED: a slow search can no longer stall the worker for other users.
A14: BE-011 | B14: Development | C14: AI / Authorization | D14: Make destructive AI actions confirm in code, not just in the prompt | E14: cancel_booking / update_room_price / create_promo_code rely on a prompt instruction to 'ask first'. Nothing in code enforces it, so a model slip or injected text could execute them. ⏱ When it surfaces: If a guest/hotelier message is crafted to trick the model, or the model mis-fires. | F14: Confirmation is a prompt convention, not a code gate. | G14: Require an explicit 2-step confirmation token in code before any mutating tool runs; gate price/promo behind OWNER/MANAGER. | H14: High | I14: Open | J14: Backend Dev | K14: 10/06/2026 | O14: =IF(AND(K14<>"",M14<>""),M14-K14,"") | P14: Hardening: removes the chance of an AI-initiated cancellation or rate change without a real confirmation. (Tenant scope already enforced.)
A15: BE-012 | B15: Development | C15: AI / Security | D15: Harden the bots against prompt injection | E15: Guest chat text reaches a tool-enabled LLM, and chain guest_history (incl. guest special_requests) is injected into the system prompt — a path for second-order injection. ⏱ When it surfaces: As real guests (and the occasional bad actor) type free-form messages. | F15: Untrusted text concatenated into prompts that can drive tools. | G15: Treat guest/stored text as untrusted; sanitise before insertion; keep public-bot tools read-only; add injection tests. | H15: Medium | I15: Open | J15: Backend Dev | K15: 10/06/2026 | O15: =IF(AND(K15<>"",M15<>""),M15-K15,"") | P15: Protects against the bot being steered to misquote prices/policies or reveal unintended info.
A16: BE-013 | B16: Development | C16: AI / Bookings | D16: Re-check availability inside AI quick-booking | E16: create_quick_booking writes a Booking without an inventory/overlap check (availability is a separate optional tool the model may skip). ⏱ When it surfaces: When the AI books a date range that's actually sold out. | F16: Booking tool does not re-validate availability atomically. | G16: Re-check availability inside create_quick_booking and reject on conflict. | H16: Medium | I16: Open | J16: Backend Dev | K16: 10/06/2026 | O16: =IF(AND(K16<>"",M16<>""),M16-K16,"") | P16: Prevents AI-driven overbooking and the resulting walk/compensation cost.
A17: BE-014 | B17: Development | C17: Performance | D17: Optimise availability counting (currently in-Python loops) | E17: check_availability does an O(bookings*rooms) Python loop over overlapping bookings (rooms are stored as a JSON array). ⏱ When it surfaces: On large/busy hotels with many overlapping bookings. | F17: In-memory aggregation; fine for small data, heavier as bookings grow. | G17: Pre-aggregate counts; ensure composite index on (hotel_id, status, dates). | H17: Medium | I17: Open | J17: Backend Dev | K17: 10/06/2026 | O17: =IF(AND(K17<>"",M17<>""),M17-K17,"") | P17: Keeps the booking funnel and concurrent chats fast as data volume grows.
A18: BE-015 | B18: Development | C18: AI / Accuracy | D18: Validate AI-quoted prices/policies against the DB | E18: The bots generate free text; tools exist but nothing guarantees a quoted price/policy exactly matches the DB. (Checkout already re-validates price server-side.) ⏱ When it surfaces: When a guest asks detailed price/policy questions and the model paraphrases. | F18: Generative output is not constrained to tool data. | G18: Post-check any price/availability the model states before sending it to the guest. | H18: Medium | I18: Open | J18: Backend Dev | K18: 10/06/2026 | O18: =IF(AND(K18<>"",M18<>""),M18-K18,"") | P18: Reduces the risk of a guest treating a wrong AI quote as a commitment.
A19: BE-016 | B19: Development | C19: AI / UX | D19: Make chart data flow through code, not model echo | E19: agent.py asks the model to echo [CHART_DATA] JSON verbatim; smaller models sometimes reword or drop it. ⏱ When it surfaces: Intermittently, depending on the model and prompt. | F19: Structured output delegated to model obedience. | G19: Return chart data via a dedicated field the UI reads directly. | H19: Low | I19: Open | J19: Backend Dev | K19: 10/06/2026 | O19: =IF(AND(K19<>"",M19<>""),M19-K19,"") | P19: Dashboard charts render reliably -> hoteliers trust the analytics.
A20: BE-017 | B20: Development | C20: AI / Config | D20: Require explicit AI provider instead of key-prefix guessing | E20: Provider is inferred from key prefixes (gsk_/sk-/AIza); a custom gateway or new key format breaks selection. ⏱ When it surfaces: When a hotel rotates keys or uses a non-standard provider. | F20: Heuristic detection instead of explicit config. | G20: Require ai_provider; use prefix detection only as a logged last resort. | H20: Low | I20: Open | J20: Backend Dev | K20: 10/06/2026 | O20: =IF(AND(K20<>"",M20<>""),M20-K20,"") | P20: Avoids a hotel's AI silently routing to the wrong API after a key change.
A21: BE-018 | B21: Development | C21: AI / Cost | D21: Confirm model tiering for the hotelier assistant | E21: The hotelier assistant defaults to a 70B model. Policy allows a large model for the analytics agent; confirm whether general assistant traffic should use the cheap model with large reserved for heavy analytics. ⏱ When it surfaces: Linearly with hotelier assistant adoption. | F21: Default model choice vs cost policy needs a product decision. | G21: Default general queries to the cheap model; route only heavy analytics to 70B. | H21: Low | I21: Open | J21: Backend Dev | K21: 10/06/2026 | O21: =IF(AND(K21<>"",M21<>""),M21-K21,"") | P21: Optional cost optimisation; pairs with the AI-budget item.
A22: BE-019 | B22: Development | C22: Privacy / Logging | D22: Stop logging PII at INFO in the auth path | E22: deps.py logged email/supabase_id at INFO on several auth branches; policy is DEBUG-only / hashed. ⏱ When it surfaces: Continuously in production logs until changed. | F22: Verbose INFO logging of identifiers on the hot auth path. | G22: Drop to DEBUG / log non-PII identifiers; keep LOG_LEVEL=WARNING in prod. | H22: Medium | I22: Resolved | J22: Backend Dev | K22: 10/06/2026 | M22: 10/06/2026 | N22: deps.py auth logs with email/supabase_id moved to DEBUG; master-admin promotion now logs user_id instead of email. | O22: =IF(AND(K22<>"",M22<>""),M22-K22,"") | P22: FIXED: lowers PII exposure and log egress cost.
A23: BE-020 | B23: Development | C23: Reliability / SSE | D23: Add a max lifetime + disconnect check to streaming chat | E23: stream_guest_ai streams agent events with no overall timeout and holds the DB session for the whole stream; only tool_call_limit bounds it. ⏱ When it surfaces: With abandoned/idle streaming chats or deliberate slow clients. | F23: Missing max-duration and client-disconnect handling on the SSE generator. | G23: Add a hard stream lifetime + disconnect detection; release the session before streaming. | H23: Medium | I23: Open | J23: Backend Dev | K23: 10/06/2026 | O23: =IF(AND(K23<>"",M23<>""),M23-K23,"") | P23: Frees worker+DB resources held by dead streams; raises real concurrency.
A24: BE-021 | B24: Development | C24: Observability | D24: Strengthen AI usage accounting | E24: record_ai_usage swallows all errors and returns 0 if metrics/Redis are missing, so a failed run may record nothing. ⏱ When it surfaces: When Redis or metrics are briefly unavailable. | F24: Telemetry is best-effort with no fallback/alert. | G24: Emit a metric on accounting failures; keep a durable aggregate beyond Redis. | H24: Low | I24: Open | J24: Backend Dev | K24: 10/06/2026 | O24: =IF(AND(K24<>"",M24<>""),M24-K24,"") | P24: Keeps cost dashboards trustworthy so overspend isn't hidden.
A25: BE-022 | B25: Development | C25: Error Handling | D25: Stop returning raw exception text to clients | E25: The assistant endpoint returned HTTP 500 with detail=f'AI Agent Error: {str(e)}', leaking internal error text. ⏱ When it surfaces: On any unhandled agent error. | F25: Generic except surfaced internal detail in the response. | G25: Return a generic message; log detail server-side. | H25: Medium | I25: Resolved | J25: Backend Dev | K25: 10/06/2026 | M25: 10/06/2026 | N25: api/v1/agent.py now returns generic 500/503 messages and logs full detail server-side with exc_info. | O25: =IF(AND(K25<>"",M25<>""),M25-K25,"") | P25: FIXED: no internal stack/library detail leaks to callers.
A26: BE-023 | B26: Post-Development | C26: Scaling / Outage | D26: Protect against DB connection exhaustion under a traffic burst | E26: SCALE_TUNING.md flags Postgres connections as the #1 crash risk. A burst of page loads (search + availability + chat warm) on one popular hotel can pressure the pool (default ~10/worker). ⏱ When it surfaces: When ~100 users hit one hotel page at once (campaign/QR/sale). | F26: Small connection budget + AI requests holding connections longer. | G26: Right-size pool/concurrency under the Supabase limit; release sessions early; add a CDN/cache for public reads. | H26: High | I26: Open | J26: Backend Dev | K26: 10/06/2026 | O26: =IF(AND(K26<>"",M26<>""),M26-K26,"") | P26: Prevents one hotel's success from degrading the whole platform.
A27: BE-024 | B27: Post-Development | C27: Abuse / Cost | D27: Add a non-spoofable signal to the public AI chat | E27: chat/guest is anonymous; the 5/min IP limit is spoofable and the real cap is 1000 LLM calls/hotel/day (which fails open without Redis). ⏱ When it surfaces: If a bot targets the public widget, or it's left open and looping. | F27: Spoofable IP limit + fail-open quota on an unauthenticated, cost-bearing endpoint. | G27: Add a signed widget token / captcha, a fail-closed quota, and a platform-wide spend breaker. | H27: High | I27: Open | J27: Backend Dev | K27: 10/06/2026 | O27: =IF(AND(K27<>"",M27<>""),M27-K27,"") | P27: Caps the worst-case LLM bill from automated abuse of the public chat.
A28: BE-025 | B28: Post-Development | C28: Abuse / DoS | D28: Add a baseline rate limit to authenticated routes | E28: Login is on Supabase (no backend password endpoint), but most authenticated routes have no limiter, and invalid Bearer tokens are uncacheable so each forces a JWT verification. ⏱ When it surfaces: Under a deliberate token-flood. | F28: Rate limiting applied selectively; auth verify cost paid per garbage-token request. | G28: Add an IP+token baseline limit; short-cache negative verifications; alert on auth-error spikes. | H28: Medium | I28: Open | J28: Backend Dev | K28: 10/06/2026 | O28: =IF(AND(K28<>"",M28<>""),M28-K28,"") | P28: Keeps latency stable for real hoteliers during an auth-spam attempt.
A29: BE-026 | B29: Post-Development | C29: Reliability / SPOF | D29: Make Redis highly available | E29: Payment idempotency, rate limits, AI quota, auth cache and analytics caches all rely on a single Redis instance (SCALE_TUNING notes HA is needed before relying on it for payment idempotency). ⏱ When it surfaces: During any Redis outage. | F29: No Redis HA; several controls degrade on its loss. | G29: Move to managed HA Redis; define explicit degraded-mode behaviour per control. | H29: High | I29: Open | J29: Backend Dev | K29: 10/06/2026 | O29: =IF(AND(K29<>"",M29<>""),M29-K29,"") | P29: Removes a single point that simultaneously weakens abuse limits, AI quota and payment idempotency.
A30: BE-027 | B30: Post-Development | C30: Cost Monitoring | D30: Automate per-hotel AI spend alerting | E30: The ai_tokens counters exist but must be read manually; no threshold alert or auto-throttle. ⏱ When it surfaces: As AI usage scales and one hotel/bot spikes. | F30: Monitoring is manual. | G30: Add daily aggregation + alerts + optional auto-throttle at the tier budget. | H30: Medium | I30: Open | J30: Backend Dev | K30: 10/06/2026 | O30: =IF(AND(K30<>"",M30<>""),M30-K30,"") | P30: Overspend is caught in hours, not on the monthly invoice.
A31: BE-028 | B31: Post-Development | C31: Cost / Scale | D31: Raise AI cache hit-rate to flatten cost growth | E31: Each guest message is 1-2 LLM calls; only a short-TTL cache dedupes. Cost grows with visitor volume. ⏱ When it surfaces: As marketing succeeds and visitor numbers climb. | F31: Variable per-message LLM cost with limited dedup. | G31: Increase cache hit-rate, keep prompts/history tight (history already capped at 20), set a platform spend breaker. | H31: Medium | I31: Open | J31: Backend Dev | K31: 10/06/2026 | O31: =IF(AND(K31<>"",M31<>""),M31-K31,"") | P31: Keeps AI cost growing slower than traffic.
A32: BE-029 | B32: Post-Development | C32: External Dependencies | D32: Add timeouts/retries + alerting to third-party calls | E32: Weather, DuckDuckGo, Razorpay, Google Sheets (fire-and-forget) and Meta can fail; some failures are swallowed (sheet sync), losing data silently. ⏱ When it surfaces: During any provider outage or slowdown. | F32: No circuit breakers/retries; fire-and-forget drops failures. | G32: Add timeouts, retries with backoff, and a dead-letter/alert for failed syncs. | H32: Medium | I32: Open | J32: Backend Dev | K32: 10/06/2026 | O32: =IF(AND(K32<>"",M32<>""),M32-K32,"") | P32: Prevents silent lead-data loss and provider-outage error spikes for guests.
A33: BE-030 | B33: Post-Development | C33: Data Quality | D33: Validate ingested competitor rates (rate-shopper) | E33: Rate-shopping data comes from the Chrome extension; if it stalls or sends bad data, pricing advice rests on stale/garbage rates. ⏱ When it surfaces: When the scraper breaks or a competitor site changes. | F33: External ingestion with limited validation. | G33: Validate/timestamp ingested rates; flag stale data; bound ingestion volume. | H33: Medium | I33: Open | J33: Backend Dev | K33: 10/06/2026 | O33: =IF(AND(K33<>"",M33<>""),M33-K33,"") | P33: Keeps AI pricing recommendations based on fresh, sane data.
A34: BE-031 | B34: Post-Development | C34: Payments / Security | D34: Keep payment webhook signature verification locked down | E34: Payment confirmation trusts HMAC-verified webhooks (Razorpay/Meta). This must stay correct as code evolves. ⏱ When it surfaces: Only if a future change weakens verification. | F34: Security-critical path that must not regress. | G34: Add tests asserting signature rejection; alert on verification failures; keep strict per-hotel keys. | H34: High | I34: Open | J34: Backend Dev | K34: 10/06/2026 | O34: =IF(AND(K34<>"",M34<>""),M34-K34,"") | P34: Protects directly against spoofed 'paid' events / financial loss.
A35: BE-032 | B35: Post-Development | C35: Multi-tenancy | D35: Add automated tests for tenant isolation in AI tools | E35: AI tools filter by user.hotel_id today; a future tool that forgets the filter would leak/modify another hotel's data. ⏱ When it surfaces: Only if a future tool drops the hotel_id filter. | F35: Isolation enforced per-query; easy to miss on new tools. | G35: Add a shared tenant-scoping helper + tests asserting cross-hotel access is blocked for every AI tool. | H35: High | I35: Open | J35: Backend Dev | K35: 10/06/2026 | O35: =IF(AND(K35<>"",M35<>""),M35-K35,"") | P35: Locks in the core 'one hotel never sees another' guarantee against regressions.
A36: BE-033 | B36: Post-Development | C36: Memory / Cost | D36: Offload report/PDF generation to a background worker | E36: Reports load pandas/matplotlib/reportlab (lazy but heavy) in-request; concurrent exports inflate per-worker RAM. ⏱ When it surfaces: When several hoteliers export analytics at once on a small box. | F36: Heavy, CPU/RAM-intensive work done in the request path. | G36: Move generation to a background worker/queue; cap concurrency. | H36: Medium | I36: Open | J36: Backend Dev | K36: 10/06/2026 | O36: =IF(AND(K36<>"",M36<>""),M36-K36,"") | P36: Avoids worker OOM/restarts dropping in-flight requests.
A37: BE-034 | B37: Post-Development | C37: Monitoring | D37: Alert when the AI falls back to its canned error message | E37: On failure the bots return friendly text and log the error; without alerting, sustained failures look like normal traffic. ⏱ When it surfaces: During a quiet AI/provider outage. | F37: Graceful degradation without a paired alert. | G37: Emit an error metric whenever the canned fallback fires; alert on rate. | H37: Low | I37: Open | J37: Backend Dev | K37: 10/06/2026 | O37: =IF(AND(K37<>"",M37<>""),M37-K37,"") | P37: The AI can't be silently down for hours; issues surface before customers complain.

Sheet Load & Cost Scenarios
A1: ⚡ Load, Abuse & Cloud-Cost Scenarios — 'what happens if…'
A2: Scenario | B2: Trigger | C2: What happens technically (code-grounded) | D2: Business impact | E2: Current safeguard | F2: Recommended hardening
A3: 100 users on one hotel page at once | B3: Campaign/QR/sale drives a burst to one page. | C3: Each visit can fire room search + availability + AI widget warm. Availability counts in Python; AI chat holds a DB connection for the whole LLM call. Default pool ~10/worker. | D3: If the pool saturates, requests queue/timeout -> 500s for ALL hotels until it drains. | E3: Per-worker pool, lazy heavy imports, short caches, documented connection math, 60-120/min public read limits. | F3: Release DB session before the LLM call; CDN/cache public reads; right-size pool/concurrency; run the load test.
A4: Bot spams the public AI chat | B4: Anonymous attacker scripts the widget, rotating X-Forwarded-For. | C4: 5/min IP limit is spoofable; backstop is 1000 LLM calls/hotel/day, which fails open without Redis. Each message = 1-2 LLM calls. | D4: Worst-case a few $/day of LLM per targeted hotel; bounded by the daily cap unless Redis is down. | E4: Per-hotel daily cap (1000), feature flag, cheap 8B model, token accounting, fixed cheap fallback. | F4: Signed widget token/captcha; fail-closed quota; platform-wide spend breaker.
A5: Someone spams the backend auth | B5: Flood of authenticated routes with garbage Bearer tokens. | C5: Login is on Supabase (no backend password endpoint). Invalid tokens are uncacheable so each runs a JWT verify; most authed routes have no rate limit. | D5: CPU + Supabase auth load climb; latency degrades for real hoteliers. | E5: Valid-token payload caching; active-session tracking; Supabase verifies signature+exp; PII now logged at DEBUG. | F5: Baseline IP+token limit on authed routes; short negative-cache; alert on auth-error spikes.
A6: Redis goes down | B6: Single Redis instance restarts/blips. | C6: Rate limits, AI quota, auth cache, slug/analytics caches and payment idempotency degrade; quota+limits fail open. | D6: Abuse/cost protection drops; payment idempotency loss risks double-charges. | E6: Best-effort try/except keeps the app serving. | F6: Managed HA Redis; explicit fail-closed for cost/payment controls; Redis health alerting.
A7: AI adoption grows (marketing works) | B7: More guests use the concierge across more hotels. | C7: Variable cost = 1-2 LLM calls/message; limited dedup (short cache). | D7: LLM bill grows with traffic; margins compress without a budget. | E7: Cheap 8B default on guest bot, history capped at 20, tool/token caps, usage counters. | F7: Per-tier budget + auto-throttle; higher cache hit-rate; bill pass-through decision.
A8: Concurrent report/PDF exports | B8: Several hoteliers export analytics at once. | C8: pandas/matplotlib/reportlab load per worker (lazy but heavy); CPU/RAM intensive in-request. | D8: Small boxes can OOM and restart workers, dropping in-flight requests. | E8: Lazy imports keep idle RAM low. | F8: Background worker/queue for generation; cap concurrent exports.

Sheet CI-CD Pipeline
A1: 🔄 CI/CD Pipeline — automated quality gates
A2: GitHub Actions runs on every Pull Request and on pushes to main/develop/feature branches. A change cannot merge unless these gates pass — this is what stops a bug like the AI-assistant crash from ever reaching production again.
A3: Stage | B3: Tool / Action | C3: What it checks | D3: Why it matters here
A4: Trigger | B4: GitHub Actions (push + pull_request) | C4: Runs automatically on PRs and branch pushes (main/develop/claude/**). | D4: Every change is checked before merge, not after deploy.
A5: Backend - Install | B5: pip install -r requirements.txt (Python 3.11) | C5: Dependencies resolve and install cleanly. | D5: Catches broken/missing dependencies early.
A6: Backend - Compile | B6: python -m compileall app main.py | C6: Fast-fails on any syntax or import error across the backend. | D6: Would have instantly caught the missing-logger class of bug.
A7: Backend - Tests | B7: pytest tests/ (253 passing) | C7: Runs the full backend suite incl. the new AI smoke/regression tests. | D7: Pins the AI-assistant fix and guards multi-tenant/payment behaviour.
A8: Frontend - Types | B8: tsc --noEmit | C8: TypeScript type-checks the whole frontend. | D8: Catches UI/data-shape errors before build.
A9: Frontend - Build | B9: npm run build (Vite) | C9: Production build succeeds. | D9: Ensures the app actually ships.
A10: Frontend - E2E | B10: Playwright (chromium) | C10: End-to-end browser tests of key flows. | D10: Verifies real user journeys (incl. booking/AI UI).
A11: Artifacts | B11: upload-artifact | C11: Stores the Playwright report for 30 days. | D11: Failures are debuggable from the PR.
A12: Deploy (CD) | B12: Railway (create_all on boot) | C12: Deploys backend+frontend; DB tables via create_all. | D12: Roadmap: add a staging gate + smoke check before prod promotion.
A14: Recommended next CI/CD additions
A15: 1. Add pip-audit / npm audit (dependency vulnerability scan) as a non-blocking gate, then enforce.
A16: 2. Add a staging environment + automated smoke test before promoting to production (true CD).
A17: 3. Add coverage reporting and a minimum threshold so AI/payment paths stay tested.
A18: 4. Add a secrets-scanning step (e.g. gitleaks) to prevent keys being committed.

Sheet Team & Hiring
A1: 👥 Team & Hiring Recommendation
A2: Recommendation: YES — hire one Backend Engineer (priority) and one Frontend Engineer. The platform is large (~70 routers, 250+ endpoints, payments, multi-tenant, AI). The critical AI-assistant bug is already fixed; the remaining roadmap is mostly backend reliability/cost/security plus frontend UX/perf. Dedicated owners make the Hypercare SLAs achievable.
A3: Role | B3: Why needed (tied to issues) | C3: What they own in THIS project | D3: First 30 / 60 / 90 days
A4: Backend Engineer (Python/FastAPI) — PRIORITY | B4: Owns the High/Medium backend roadmap: DB session held during LLM (BE-008), code-level confirmation on mutating tools (BE-011), prompt-injection hardening (BE-012), AI abuse/rate limits (BE-024/025), Redis HA (BE-026), tenant-isolation tests (BE-032), webhook integrity (BE-031). | C4: FastAPI services, AI agents (agno), Postgres performance & indexing, Redis, payments/Razorpay, multi-tenant security, rate limiting, cost controls, tests, observability. | D4: 30d: rate-limit authed routes, ship fail-closed AI quota. 60d: release DB session before LLM, prompt-injection + code confirmations, SQL-aggregate availability. 90d: cost alerts/auto-throttle, Redis HA, load test + scaling tune.
A5: Frontend Engineer (React/Vite) | B5: Owns the guest booking experience and hotelier dashboard quality: chart pipeline (BE-016), AI chat/streaming UX, graceful error/loading states, and the conversion-critical booking funnel. | C5: React/Vite app, booking engine UI, AI chat widget + SSE streaming UI, analytics charts, error/empty/loading states, accessibility, performance (bundle/CDN), frontend telemetry. | D5: 30d: robust error/loading states for AI + booking; fix chart rendering. 60d: streaming UX + disconnect handling; booking funnel polish. 90d: performance + accessibility pass; funnel drop-off analytics.
A6: (Optional) Fractional DevOps / SRE | B6: Infra-flavoured items: Redis HA (BE-026), pool exhaustion (BE-023), trusted proxy/WAF (BE-002/024), load test (BE-004), report worker (BE-033). | C6: Railway/infra, Supabase connection budget, Redis HA, CDN/WAF, monitoring/alerting (Sentry), CI/CD, load testing. | D6: Can be contract or absorbed by the senior backend hire initially; formalise before scaling traffic.

Sheet Phase Plan
A1: 🏨 Booking Engine — Phase-wise Delivery Plan
A2: Phase | B2: Milestone / Activity | C2: Owner | D2: Start Date | E2: End Date | F2: Duration (days) | G2: Status | H2: Notes
A3: Pre-Development | B3: Architecture & cost-governance review (AI budget, trust model) | C3: Tech Lead | G3: Not Started
A4: Pre-Development | B4: Capacity plan + DB connection budget vs Supabase limit | C4: Backend Dev | G4: Not Started
A5: Pre-Development | B5: Run load test at expected peak (scripts/load_test.py) | C5: DevOps | G5: Not Started
A6: Pre-Development | B6: Hiring: backend + frontend engineers | C6: Founder | G6: Not Started | H6: See Team sheet
A7: Pre-Development | B7: Define abuse/rate-limit & fail-closed policy | C7: Backend Dev | G7: Not Started
A8: Development | B8: Fix AI assistant crash (logger) + smoke tests | C8: Backend Dev | D8: 10/06/2026 | E8: 10/06/2026 | F8: 0 | G8: Completed | H8: DONE - 253 tests green
A9: Development | B9: Cheap-model error fallback + web-search timeout | C9: Backend Dev | D9: 10/06/2026 | E9: 10/06/2026 | F9: 0 | G9: Completed | H9: DONE
A10: Development | B10: Sanitise error responses + PII logging to DEBUG | C10: Backend Dev | D10: 10/06/2026 | E10: 10/06/2026 | F10: 0 | G10: Completed | H10: DONE
A11: Development | B11: Release DB session before LLM round-trip | C11: Backend Dev | G11: Not Started
A12: Development | B12: Prompt-injection hardening + code-level confirmations | C12: Backend Dev | G12: Not Started
A13: Development | B13: Performance: SQL aggregation + indexes | C13: Backend Dev | G13: Not Started
A14: Development | B14: Frontend: chart pipeline, error/loading UX | C14: Frontend Dev | G14: Not Started
A15: Development | B15: QA + automated coverage for AI/payment paths | C15: Both Devs | G15: Not Started
A16: Post-Development | B16: Redis HA + fail-closed quota | C16: DevOps | G16: Not Started
A17: Post-Development | B17: Cost monitoring + per-hotel spend alerts | C17: Backend Dev | G17: Not Started
A18: Post-Development | B18: WAF / signed widget token / captcha for public AI | C18: Backend Dev | G18: Not Started
A19: Post-Development | B19: Scaling tune (pool/concurrency/replicas) + CDN | C19: DevOps | G19: Not Started
A20: Post-Development | B20: Hypercare monitoring & SLA tracking (30 days) | C20: Both Devs | G20: Not Started
A21: Post-Development | B21: Background worker for reports/PDF + dead-letter syncs | C21: Backend Dev | G21: Not Started
A22: Post-Development | B22: CI/CD: staging gate + dependency/secret scanning | C22: DevOps | G22: Not Started | H22: CI already on PRs

Sheet  Priority Matrix
A1: Issue Priority Matrix — Definitions & Resolution SLAs
A2: Priority | B2: Definition | C2: Examples | D2: Response SLA | E2: Resolution SLA | F2: Owner | G2: Escalation
A3: Critical | B3: Breaks core money/data flow or takes the platform down; no workaround. | C3: AI assistant 500s on every call (now fixed); DB pool exhaustion; spoofed payment webhook; cross-tenant leak. | D3: Immediate (< 1 h) | E3: 4 h (same day) | F3: Tech Lead | G3: Founder
A4: High | B4: Major feature broken or a real cost/abuse/security risk. | C4: DB connection held during LLM; public AI abuse; Redis SPOF; no rate limit on authed routes. | D4: 2 h | E4: 24 h | F4: Tech Lead | G4: Founder
A5: Medium | B5: Degraded behaviour, performance or hygiene; limited blast radius. | C5: Availability loops; SSE lifetime; PII at INFO (now fixed); provider detection. | D5: 4 h | E5: 3 business days | F5: Tech Lead | G5: Tech Lead
A6: Low | B6: Cosmetic/observability/low-likelihood; fix when convenient. | C6: Chart echo; usage accounting; canned-error alerting. | D6: Next sprint | E6: 1–2 sprints | F6: Tech Lead | G6: Tech Lead
A9: COLOUR LEGEND
A10: Critical | B10: High | C10: Medium | D10: Low | E10: Pre-Dev Phase | F10: Dev Phase | G10: Post-Dev Phase

Sheet  Dashboard
A1: Booking Engine — Issue Summary Dashboard
A2: Update the Issue Tracker sheet; this dashboard auto-calculates totals
A4: ISSUES BY STATUS | D4: ISSUES BY PRIORITY
A5: Status | B5: Count | D5: Priority | E5: Count
A6: Open | B6: =COUNTIF(' Issue Tracker'!I:I,A6) | D6: Critical | E6: =COUNTIF(' Issue Tracker'!H:H,D6)
A7: In Progress | B7: =COUNTIF(' Issue Tracker'!I:I,A7) | D7: High | E7: =COUNTIF(' Issue Tracker'!H:H,D7)
A8: Blocked | B8: =COUNTIF(' Issue Tracker'!I:I,A8) | D8: Medium | E8: =COUNTIF(' Issue Tracker'!H:H,D8)
A9: Resolved | B9: =COUNTIF(' Issue Tracker'!I:I,A9) | D9: Low | E9: =COUNTIF(' Issue Tracker'!H:H,D9)
A10: Closed | B10: =COUNTIF(' Issue Tracker'!I:I,A10)
A11: Deferred | B11: =COUNTIF(' Issue Tracker'!I:I,A11)
A12: TOTAL | B12: =SUM(B6:B11)
A14: ISSUES BY PHASE
A15: Phase | B15: Count
A16: Pre-Development | B16: =COUNTIF(' Issue Tracker'!B:B,A16)
A17: Development | B17: =COUNTIF(' Issue Tracker'!B:B,A17)
A18: Post-Development | B18: =COUNTIF(' Issue Tracker'!B:B,A18)

Sheet  Timeframes
A1: Recommended Timeframes for Issue Resolution
A2: Phase | B2: Issue Type | C2: Priority | D2: Discovery Method | E2: Target Fix Window | F2: Notes
A3: Pre-Development | B3: Architecture/cost-governance gap | C3: Critical | D3: Design review | E3: Before dev | F3: Blocks safe build
A4: Pre-Development | B4: Capacity/connection planning | C4: High | D4: Load test | E4: Before go-live | F4: Sets scaling ceiling
A5: Pre-Development | B5: Trusted-proxy / IP trust | C5: High | D5: Security review | E5: Before go-live | F5: Affects every IP limit
A6: Pre-Development | B6: Team/ownership gap | C6: Medium | D6: Mgmt review | E6: This quarter | F6: Staffing decision
A7: Development | B7: AI agent crash / 500 | C7: Critical | D7: Smoke test / QA | E7: < 1 day (DONE) | F7: Was feature-down; fixed
A8: Development | B8: Connection held during LLM | C8: High | D8: Load test / profiling | E8: 1 sprint | F8: Scaling root cause
A9: Development | B9: Prompt injection / tool authz | C9: High | D9: Security test | E9: < 1 sprint | F9: Money/data at risk
A10: Development | B10: Performance (loops/N+1) | C10: Medium | D10: Profiling | E10: 1-2 sprints | F10: Latency under load
A11: Development | B11: Cost (model/fallback) | C11: High | D11: Cost review | E11: DONE | F11: Fixed: cheap fallback
A12: Development | B12: Privacy/logging hygiene | C12: Medium | D12: Code review | E12: DONE | F12: Fixed: PII to DEBUG
A13: Post-Development | B13: Pool exhaustion / outage | C13: Critical | D13: Monitoring/alert | E13: Immediate (<1h) | F13: Hypercare SLA
... A20: Post-Development | B20: Observability gaps | C20: Low | D20: Metrics | E20: Next sprint | F20: Slow detection

Sheet How to Use
A1: How to Use This Tracker
A3: Issue Tracker | B3: Main working sheet. Add every bug/error here. • Use dropdown menus for Phase, Priority and Status columns. • ID is auto-assigned (BE-001, BE-002 …); enter dates in DD/MM/YYYY. • Time to Fix calculates automatically once Reported & Resolved dates are filled. • Keep 'Resolution Notes' updated — the team will use it as a knowledge base.
A4: Phase Plan | B4: High-level delivery roadmap. • Add Start and End dates for each milestone — Duration auto-calculates. • Use the Status dropdown (Not Started / In Progress / Completed / Blocked / Deferred). • Update regularly during sprint reviews.
A5: Priority Matrix | B5: Reference sheet — do not edit. • Defines what Critical / High / Medium / Low mean for this project. • Response and Resolution SLAs are binding during Hypercare (30 days post-launch). • Use the colour legend at the bottom when reviewing any sheet.
A6: Dashboard | B6: Auto-calculated summary — do not edit directly. • Counts update as you fill in the Issue Tracker. • Share a screenshot of this tab in weekly status reports. • If counts look wrong, ensure Phase / Priority / Status values match the dropdowns exactly.
A7: Timeframes | B7: SLA reference for every combination of phase and priority. • Use this when setting Target Dates in the Issue Tracker. • Deviation from these windows must be approved by the Tech Lead and logged in Remarks.
A8: How to Use | B8: This sheet. Pin to your browser tab and share with all team members before the first sprint.
